src/__init__.py
src/c3tt_rpc_client.py
c3tt_rpc_client-1.0.dist-info/LICENSE
c3tt_rpc_client-1.0.dist-info/METADATA
c3tt_rpc_client-1.0.dist-info/WHEEL
c3tt_rpc_client-1.0.dist-info/top_level.txt
c3tt_rpc_client-1.0.dist-info/zip-safe
c3tt_rpc_client-1.0.dist-info/RECORD
