Metadata-Version: 2.1
Name: c3tt_rpc_client
Version: 1.0
Summary: Client-Library for https://github.com/crs-tools/tracker
Home-page: https://github.com/voc/c3tt_rpc_client
Author: C3VOC
Author-email: voc+pypi@c3voc.de
Classifier: Programming Language :: Python :: 3
Classifier: License :: OSI Approved :: GNU General Public License v3 or later (GPLv3+)
Classifier: Operating System :: OS Independent
Classifier: Development Status :: 5 - Production/Stable
License-File: LICENSE
